cheat_sh/__init__.py
cheat_sh-0.0.2.dist-info/METADATA
cheat_sh-0.0.2.dist-info/WHEEL
cheat_sh-0.0.2.dist-info/top_level.txt
cheat_sh-0.0.2.dist-info/RECORD
