Metadata-Version: 2.1
Name: cheat-sh
Version: 0.0.2
Summary: wrapper around http://cheat.sh
Home-page: https://github.com/SingularChatelet/cheat_sh
Author: Saverio
Author-email: Saverio <personnex976@gmail.com>
License: MIT
Project-URL: Bug Tracker, https://github.com/SingularChatelet/cheat_sh/issues/new/choose
Keywords: cheatsh,cheat.sh,cht.sh
Classifier: Programming Language :: Python :: 3
Classifier: License :: OSI Approved :: MIT License
Classifier: Operating System :: OS Independent
Requires-Python: >=3.7
Requires-Dist: requests
